specauto/__init__.py
specauto/core.py
specauto/estimation/__init__.py
specauto/estimation/hac.py
specauto/estimation/ols.py
specauto/output/__init__.py
specauto/output/tables.py
specauto/simulation/__init__.py
specauto/simulation/critical_values.py
specauto/tests/__init__.py
specauto/tests/ar_structure.py
specauto/tests/misspecification.py
specauto/tests/serial_independence.py
specauto-1.0.2.dist-info/licenses/LICENSE
specauto-1.0.2.dist-info/METADATA
specauto-1.0.2.dist-info/WHEEL
specauto-1.0.2.dist-info/top_level.txt
specauto-1.0.2.dist-info/RECORD
